aliasing-0.4.2.dist-info/METADATA
aliasing-0.4.2.dist-info/WHEEL
aliasing-0.4.2.dist-info/licenses/LICENSE
aliasing/__init__.py
aliasing/core.py
aliasing/error.py
aliasing/virtual_alias.py
aliasing-0.4.2.dist-info/RECORD
